{"version":1,"addresses":[{"guid":"246c2befd584","version":1,"timeCreated":1772391126948,"timeLastUsed":1772391126950,"timeLastModified":1772391126948,"timesUsed":1,"name":"Farshad Islam","street-address":"16 Royal Oak Terrace NW","address-level2":"Calgary","address-level1":"BC","postal-code":"T3G 6A5","country":"CA","tel":"+14032104921","email":"fmislam.3105@gmail.com","_sync":{"changeCounter":0,"lastSyncedFields":{}},"given-name":"Farshad","additional-name":"","family-name":"Islam","address-line1":"16 Royal Oak Terrace NW","address-line2":"","address-line3":"","address-housenumber":"16","country-name":"Canada","tel-country-code":"+1","tel-national":"4032104921","tel-area-code":"403","tel-local":"2104921","tel-local-prefix":"210","tel-local-suffix":"4921"},{"guid":"467a19bbf2de","version":1,"timeCreated":1776491105314,"timeLastUsed":1776491105318,"timeLastModified":1776491105314,"timesUsed":1,"name":"Islam, Farshad","street-address":"16 Royal Oak Terrace NW","address-level2":"Calgary","address-level1":"Alberta","postal-code":"T3G 6A5","country":"CA","email":"fmislam.3105@gmail.com","_sync":{"changeCounter":0,"lastSyncedFields":{}},"given-name":"Islam","additional-name":"","family-name":"Farshad","address-line1":"16 Royal Oak Terrace NW","address-line2":"","address-line3":"","address-housenumber":"16","country-name":"Canada","tel-country-code":"","tel-national":"","tel-area-code":"","tel-local":"","tel-local-prefix":"","tel-local-suffix":""},{"guid":"f8efe56d8fb3","version":1,"timeCreated":1771548871457,"timeLastUsed":1771548871464,"timeLastModified":1771548871457,"timesUsed":1,"name":"Farshad Islam","street-address":"16 Royal Oak Terrace NW","address-level2":"Calgary","address-level1":"AB","postal-code":"T3G 6A5","country":"CA","tel":"+14032104921","email":"fmislam.3105@gmail.com","_sync":{"changeCounter":0,"lastSyncedFields":{}},"given-name":"Farshad","additional-name":"","family-name":"Islam","address-line1":"16 Royal Oak Terrace NW","address-line2":"","address-line3":"","address-housenumber":"16","country-name":"Canada","tel-country-code":"+1","tel-national":"4032104921","tel-area-code":"403","tel-local":"2104921","tel-local-prefix":"210","tel-local-suffix":"4921"}],"creditCards":[{"guid":"a51dc0ff67e4","cc-number":"************6367","cc-exp-month":5,"cc-exp-year":2029,"cc-type":"visa","version":3,"timeCreated":1774417839647,"timeLastModified":1779714150845,"timeLastUsed":1779714150852,"timesUsed":2,"cc-name":"Farshad M Islam","cc-given-name":"Farshad","cc-additional-name":"M","cc-family-name":"Islam","cc-exp":"2029-05","cc-number-encrypted":"mXuh1brCcoBIUPXSAX5bIsDNlDFbyL9U7NrNZ+TM6DtG2yHE6HlS7nKImeg=","_sync":{"changeCounter":0,"lastSyncedFields":{}}},{"guid":"ade5e2775bb8","cc-name":"Farshad M Islam","cc-number":"************9992","cc-exp-month":4,"cc-exp-year":2029,"cc-type":"visa","version":3,"timeCreated":1773293606532,"timeLastModified":1773293606532,"timeLastUsed":1773293606595,"timesUsed":1,"cc-given-name":"Farshad","cc-additional-name":"M","cc-family-name":"Islam","cc-exp":"2029-04","cc-number-encrypted":"NmTdkMdhUct9YkKsNdRwdaKS8lMla5ETTXcQTPPBIu97ZTzByLmKGlBko7I=","_sync":{"changeCounter":0,"lastSyncedFields":{}}},{"guid":"d20757af05bd","cc-number":"************7663","cc-name":"Mohammad Nahidul Islam","cc-exp-month":8,"cc-exp-year":2029,"cc-type":"mastercard","version":3,"timeCreated":1779700971789,"timeLastModified":1779700971789,"timeLastUsed":1779700971796,"timesUsed":1,"cc-given-name":"Mohammad","cc-additional-name":"Nahidul","cc-family-name":"Islam","cc-exp":"2029-08","cc-number-encrypted":"NPvTNLXjQanqa4NWQHq1HyqQaPQyHgOqL3VtJAaa5X4PjkXT0wzgraR40m0=","_sync":{"changeCounter":0,"lastSyncedFields":{}}}]}